sunflow/__init__.py
sunflow/hook.py
sunflow/io.py
sunflow/node.py
sunflow/runner.py
sunflow/scheduler.py
sunflow/test/test_sunflow.py
sunflow/test/__pycache__/test_sunflow.cpython-310.pyc
shihua_sunflow-0.1.1.dist-info/LICENSE
shihua_sunflow-0.1.1.dist-info/METADATA
shihua_sunflow-0.1.1.dist-info/WHEEL
shihua_sunflow-0.1.1.dist-info/top_level.txt
shihua_sunflow-0.1.1.dist-info/RECORD
